odoo/addons/account_invoice_import_ubl/README.rst
odoo/addons/account_invoice_import_ubl/__init__.py
odoo/addons/account_invoice_import_ubl/__manifest__.py
odoo/addons/account_invoice_import_ubl/demo/demo_data.xml
odoo/addons/account_invoice_import_ubl/i18n/account_invoice_import_ubl.pot
odoo/addons/account_invoice_import_ubl/i18n/fr.po
odoo/addons/account_invoice_import_ubl/i18n/sl.po
odoo/addons/account_invoice_import_ubl/readme/CONFIGURE.rst
odoo/addons/account_invoice_import_ubl/readme/CONTRIBUTORS.rst
odoo/addons/account_invoice_import_ubl/readme/DESCRIPTION.rst
odoo/addons/account_invoice_import_ubl/readme/USAGE.rst
odoo/addons/account_invoice_import_ubl/static/description/icon.png
odoo/addons/account_invoice_import_ubl/static/description/index.html
odoo/addons/account_invoice_import_ubl/tests/__init__.py
odoo/addons/account_invoice_import_ubl/tests/test_ubl.py
odoo/addons/account_invoice_import_ubl/tests/files/UBLInvoice-multitankcard-line_adjust.xml
odoo/addons/account_invoice_import_ubl/tests/files/UBLKetentest_Referentiefactuur_20150100.xml
odoo/addons/account_invoice_import_ubl/tests/files/efff_BE0505890632_160421_Inv_16117778.xml
odoo/addons/account_invoice_import_ubl/wizard/__init__.py
odoo/addons/account_invoice_import_ubl/wizard/account_invoice_import.py
odoo/addons/account_invoice_import_ubl/wizard/account_invoice_import_view.xml
odoo14_addon_account_invoice_import_ubl-14.0.1.0.1.dist-info/METADATA
odoo14_addon_account_invoice_import_ubl-14.0.1.0.1.dist-info/WHEEL
odoo14_addon_account_invoice_import_ubl-14.0.1.0.1.dist-info/top_level.txt
odoo14_addon_account_invoice_import_ubl-14.0.1.0.1.dist-info/RECORD
